hypervehicle/__init__.py
hypervehicle/generator.py
hypervehicle/transformations.py
hypervehicle/utilities.py
hypervehicle/vehicle.py
hypervehicle/components/__init__.py
hypervehicle/components/common.py
hypervehicle/components/component.py
hypervehicle/components/composite.py
hypervehicle/components/constants.py
hypervehicle/components/fin.py
hypervehicle/components/polygon.py
hypervehicle/components/revolved.py
hypervehicle/components/swept.py
hypervehicle/components/wing.py
hypervehicle/geometry/__init__.py
hypervehicle/geometry/geometry.py
hypervehicle/geometry/path.py
hypervehicle/geometry/surface.py
hypervehicle/geometry/vector.py
hypervehicle/hangar/__init__.py
hypervehicle/hangar/d21.py
hypervehicle/hangar/falcon9.py
hypervehicle/hangar/finner.py
hypervehicle/hangar/hifire4.py
hypervehicle/hangar/hifire8.py
hypervehicle/hangar/htv.py
hypervehicle/hangar/refex.py
hypervehicle/hangar/waverider.py
hypervehicle/hangar/wedge.py
hypervehicle/hangar/x43.py
hypervehicle-0.7.1.dist-info/COPYING
hypervehicle-0.7.1.dist-info/METADATA
hypervehicle-0.7.1.dist-info/WHEEL
hypervehicle-0.7.1.dist-info/top_level.txt
hypervehicle-0.7.1.dist-info/RECORD
