Metadata-Version: 2.1
Name: hypervehicle
Version: 0.7.1
Summary: Parametric geometry generation tool for hypersonic vehicles
Author-email: Kieran Mackle <kemackle98@gmail.com>
Project-URL: Homepage, https://github.com/kieran-mackle/hypervehicle
Project-URL: Bug Tracker, https://github.com/kieran-mackle/hypervehicle/issues
Classifier: Programming Language :: Python :: 3
Classifier: License :: OSI Approved :: GNU General Public License v3 (GPLv3)
Classifier: Operating System :: OS Independent
Requires-Python: >=3.11
License-File: COPYING
Requires-Dist: numpy-stl >=3.0.0
Requires-Dist: scipy >=1.10.0
Requires-Dist: pandas >=1.5.2
Requires-Dist: art >=5.8
Requires-Dist: tqdm >=4.64.1
Requires-Dist: multiprocess >=0.70.14
Requires-Dist: pymeshfix >=0.16.2
Provides-Extra: dev
Requires-Dist: pytest >=7.2.1 ; extra == 'dev'
Requires-Dist: black >=23.9.1 ; extra == 'dev'
Requires-Dist: commitizen >=3.10.0 ; extra == 'dev'
Requires-Dist: pre-commit >=3.4.0 ; extra == 'dev'
Requires-Dist: furo >=2022.12.7 ; extra == 'dev'
Requires-Dist: myst-parser >=0.18.1 ; extra == 'dev'
Requires-Dist: sphinx-copybutton >=0.5.1 ; extra == 'dev'
Requires-Dist: sphinx-inline-tabs >=2022.1.2b11 ; extra == 'dev'
Requires-Dist: sphinx-autobuild >=2021.3.14 ; extra == 'dev'
